minty_infra_elastic/__init__.py
minty_infra_elastic-2.0.0.dist-info/LICENSE
minty_infra_elastic-2.0.0.dist-info/METADATA
minty_infra_elastic-2.0.0.dist-info/WHEEL
minty_infra_elastic-2.0.0.dist-info/top_level.txt
minty_infra_elastic-2.0.0.dist-info/RECORD
