Metadata-Version: 2.1
Name: minty-infra-elastic
Version: 2.0.0
Summary: Infrastructure for connecting to ES from minty
Home-page: https://gitlab.com/minty-python/minty-infra-elastic
Author: Martijn van de Streek
Author-email: martijn@mintlab.nl
License: EUPL license
Keywords: minty_infra_elastic
Platform: UNKNOWN
Classifier: Development Status :: 2 - Pre-Alpha
Classifier: Intended Audience :: Developers
Classifier: License :: OSI Approved :: European Union Public Licence 1.2 (EUPL 1.2)
Classifier: Natural Language :: English
Classifier: Programming Language :: Python :: 3.6
Classifier: Programming Language :: Python :: 3.7
License-File: LICENSE
Requires-Dist: minty (~=3.0)
Requires-Dist: elasticsearch (<8.0.0,>=7.0.0)
